MANIFEST.in
setup.py
pistachio/__init__.py
pistachio/__main__.py
pistachio/dehtml.py
pistachio/pistachio.py
pistachio_mail.egg-info/PKG-INFO
pistachio_mail.egg-info/SOURCES.txt
pistachio_mail.egg-info/dependency_links.txt
pistachio_mail.egg-info/entry_points.txt
pistachio_mail.egg-info/top_level.txt