Metadata-Version: 1.0
Name: pistachio-mail
Version: 1.0.0
Summary: A simple command line tool to quickly view messages in your email.
Home-page: https://github.com/Hersh500/pistachio
Author: Hersh Sanghvi
Author-email: hersh500@gmail.com
License: UNKNOWN
Platform: UNKNOWN
